flask_htmx/__init__.py
flask_htmx/constants.py
flask_htmx/htmx.py
flask_htmx/responses.py
flask_htmx_fork-0.2.2.dist-info/LICENSE
flask_htmx_fork-0.2.2.dist-info/METADATA
flask_htmx_fork-0.2.2.dist-info/WHEEL
flask_htmx_fork-0.2.2.dist-info/RECORD
