Metadata-Version: 2.1
Name: flask-htmx-fork
Version: 0.2.2
Summary: A Flask extension to work with HTMX. Forked.
Home-page: https://github.com/edmondchuc/flask-htmx
License: MIT
Keywords: Flask,HTMX,Python,Web
Author: Edmond Chuc
Author-email: edmond.chuc@gmail.com
Requires-Python: >=3.8,<4.0
Classifier: Environment :: Web Environment
Classifier: Framework :: Flask
Classifier: Intended Audience :: Developers
Classifier: License :: OSI Approved :: MIT License
Classifier: Operating System :: OS Independent
Classifier: Programming Language :: Python
Classifier: Programming Language :: Python :: 3
Classifier: Programming Language :: Python :: 3.8
Classifier: Programming Language :: Python :: 3.9
Classifier: Programming Language :: Python :: 3.10
Classifier: Programming Language :: Python :: 3.11
Classifier: Programming Language :: Python :: 3.12
Classifier: Topic :: Internet :: WWW/HTTP :: Dynamic Content
Classifier: Topic :: Software Development :: Libraries :: Python Modules
Requires-Dist: Flask (>2.0.2)
Project-URL: Bug Tracker, https://github.com/edmondchuc/flask-htmx/issues
Project-URL: Documentation, https://flask-htmx.readthedocs.io
Project-URL: Repository, https://github.com/edmondchuc/flask-htmx
